django_ajax/__init__.py
django_ajax/decorators.py
django_ajax/encoder.py
django_ajax/middleware.py
django_ajax/mixin.py
django_ajax/models.py
django_ajax/response.py
django_ajax/shortcuts.py
django_ajax/__pycache__/__init__.cpython-39.pyc
tests/__init__.py
tests/ajaxdecorator/__init__.py
tests/ajaxdecorator/manage.py
tests/ajaxdecorator/settings.py
tests/ajaxdecorator/urls.py
tests/ajaxdecorator/app/__init__.py
tests/ajaxdecorator/app/tests.py
tests/ajaxdecorator/app/views.py
tests/ajaxmiddleware/__init__.py
tests/ajaxmiddleware/manage.py
tests/ajaxmiddleware/settings.py
tests/ajaxmiddleware/urls.py
tests/ajaxmiddleware/app/__init__.py
tests/ajaxmiddleware/app/tests.py
tests/ajaxmiddleware/app/views.py
djangoajaxswiss-4.1.dist-info/AUTHORS.rst
djangoajaxswiss-4.1.dist-info/LICENSE
djangoajaxswiss-4.1.dist-info/METADATA
djangoajaxswiss-4.1.dist-info/WHEEL
djangoajaxswiss-4.1.dist-info/top_level.txt
djangoajaxswiss-4.1.dist-info/RECORD
