Metadata-Version: 2.1
Name: djangoajaxswiss
Version: 4.1
Summary: Powerful and easy AJAX framework for django applications.
Home-page: https://github.com/AlexanderDefuria/django-ajax
Author: Alexander De Furia
Author-email: defuria.alexander@gmail.com
License: MIT
Keywords: ajax django-ajax json
Platform: OS Independent
Classifier: Environment :: Web Environment
Classifier: Framework :: Django
Classifier: Intended Audience :: Developers
Classifier: License :: OSI Approved :: MIT License
Classifier: Operating System :: OS Independent
Classifier: Programming Language :: Python
Classifier: Programming Language :: Python :: 3.9
Classifier: Topic :: Internet :: WWW/HTTP
Classifier: Topic :: Internet :: WWW/HTTP :: Dynamic Content
License-File: LICENSE
License-File: AUTHORS.rst
Requires-Dist: django (>=4.0)
